{
  "team": "Thursday_Rookies",
  "seasons": [
    "2023-2024"
  ],
  "games_played": 17,
  "record": {
    "wins": 8,
    "losses": 9,
    "ties": 0
  },
  "points": {
    "for": 110,
    "against": 97,
    "diff": 13,
    "avg_for_per_game": 6.471,
    "avg_against_per_game": 5.706
  },
  "hammer": {
    "ends": 46,
    "scoring_ends": 28,
    "two_plus_ends": 13,
    "blank_ends": 0,
    "scoring_rate": 0.609,
    "two_plus_rate": 0.283,
    "blank_rate": 0.0,
    "steals_allowed": 18
  },
  "no_hammer": {
    "ends": 73,
    "steals_for": 39,
    "steal_rate": 0.534,
    "force_exactly_one_ends": 11,
    "force_rate": 0.151,
    "defense_leq_one_ends": 52,
    "defense_leq_one_rate": 0.712
  }
}